sqlalchemy_cratedb/__init__.py
sqlalchemy_cratedb/compiler.py
sqlalchemy_cratedb/dialect.py
sqlalchemy_cratedb/predicate.py
sqlalchemy_cratedb/sa_version.py
sqlalchemy_cratedb/compat/__init__.py
sqlalchemy_cratedb/compat/api13.py
sqlalchemy_cratedb/compat/core10.py
sqlalchemy_cratedb/compat/core14.py
sqlalchemy_cratedb/compat/core20.py
sqlalchemy_cratedb/support/__init__.py
sqlalchemy_cratedb/support/pandas.py
sqlalchemy_cratedb/support/polyfill.py
sqlalchemy_cratedb/support/util.py
sqlalchemy_cratedb/type/__init__.py
sqlalchemy_cratedb/type/array.py
sqlalchemy_cratedb/type/geo.py
sqlalchemy_cratedb/type/object.py
sqlalchemy_cratedb/type/vector.py
sqlalchemy_cratedb-0.41.0.dist-info/LICENSE
sqlalchemy_cratedb-0.41.0.dist-info/METADATA
sqlalchemy_cratedb-0.41.0.dist-info/NOTICE
sqlalchemy_cratedb-0.41.0.dist-info/WHEEL
sqlalchemy_cratedb-0.41.0.dist-info/entry_points.txt
sqlalchemy_cratedb-0.41.0.dist-info/top_level.txt
sqlalchemy_cratedb-0.41.0.dist-info/RECORD
